flaskforge/__init__.py
flaskforge/flask_cli.py
flaskforge/flask_cli_tool.py
flaskforge/bases/Dockerfile
flaskforge/bases/__init__.py
flaskforge/bases/base_app.py
flaskforge/bases/base_env.py
flaskforge/bases/base_helper.py
flaskforge/bases/base_model.py
flaskforge/bases/base_resource.py
flaskforge/bases/base_runner.py
flaskforge/bases/base_schema.py
flaskforge/bases/docker-compose.yml
flaskforge/builders/__init__.py
flaskforge/builders/attribute_builder.py
flaskforge/builders/base_builder.py
flaskforge/builders/builder_factory.py
flaskforge/builders/object_builder.py
flaskforge/builders/property_builder.py
flaskforge/commands/__init__.py
flaskforge/commands/base_cli_provider.py
flaskforge/commands/create_authentication_provider.py
flaskforge/commands/create_provider.py
flaskforge/commands/create_resource_provider.py
flaskforge/commands/initapp_provider.py
flaskforge/commands/provider_factory.py
flaskforge/modifiers/__init__.py
flaskforge/modifiers/assignment_modifier.py
flaskforge/modifiers/class_modifier.py
flaskforge/modifiers/code_modifier.py
flaskforge/modifiers/field_modifier.py
flaskforge/modifiers/import_modifier.py
flaskforge/modifiers/method_modifier.py
flaskforge/utils/__init__.py
flaskforge/utils/argument.py
flaskforge/utils/commons.py
flaskforge/utils/exception.py
flaskforge/utils/io.py
flaskforge/writers/__init__.py
flaskforge/writers/app_writer.py
flaskforge/writers/base_writer.py
flaskforge/writers/helper_writer.py
flaskforge/writers/migration_writer.py
flaskforge/writers/model_writer.py
flaskforge/writers/registration_writer.py
flaskforge/writers/relationship_writer.py
flaskforge/writers/resource_writer.py
flaskforge/writers/route_writer.py
flaskforge/writers/runner_writer.py
flaskforge/writers/schema_writer.py
flaskforge/writers/swagger_writer.py
flaskforge/writers/writer_factory.py
flaskforge-1.0.6.dist-info/METADATA
flaskforge-1.0.6.dist-info/WHEEL
flaskforge-1.0.6.dist-info/entry_points.txt
flaskforge-1.0.6.dist-info/top_level.txt
flaskforge-1.0.6.dist-info/RECORD
