Metadata-Version: 2.1
Name: flaskforge
Version: 1.0.6
Summary: A CLI tool for generating Flask resources
Home-page: https://github.com/kimseasok/flaskforge
Author: Kimsea Sok
Author-email: basicblogtalk@gmail.com
License: UNKNOWN
Platform: UNKNOWN
Classifier: Development Status :: 3 - Alpha
Classifier: Intended Audience :: Developers
Classifier: License :: OSI Approved :: MIT License
Classifier: Programming Language :: Python :: 3
Classifier: Programming Language :: Python :: 3.8
Classifier: Programming Language :: Python :: 3.9
Classifier: Programming Language :: Python :: 3.10
Classifier: Programming Language :: Python :: 3.11
Requires-Python: >=3.8
Requires-Dist: Flask-RESTful (==0.3.10)
Requires-Dist: Flask (==3.0.3)
Requires-Dist: Jinja2 (==3.1.4)
Requires-Dist: MarkupSafe (==2.1.5)
Requires-Dist: PyYAML (==6.0.2)
Requires-Dist: SQLAlchemy (==2.0.31)
Requires-Dist: Werkzeug (==3.0.3)
Requires-Dist: alembic (==1.13.2)
Requires-Dist: aniso8601 (==9.0.1)
Requires-Dist: apispec (==6.6.1)
Requires-Dist: astor (==0.8.1)
Requires-Dist: bcrypt (==4.2.0)
Requires-Dist: black (==24.4.2)
Requires-Dist: blinker (==1.8.2)
Requires-Dist: click (==8.1.7)
Requires-Dist: flask-apispec (==0.11.4)
Requires-Dist: flask-jwt-extended (==4.6.0)
Requires-Dist: greenlet (==3.0.3)
Requires-Dist: inflect (==7.3.1)
Requires-Dist: itsdangerous (==2.2.0)
Requires-Dist: marshmallow (==3.21.3)
Requires-Dist: mypy-extensions (==1.0.0)
Requires-Dist: packaging (==24.1)
Requires-Dist: pathspec (==0.12.1)
Requires-Dist: platformdirs (==4.2.2)
Requires-Dist: psycopg2-binary (==2.9.9)
Requires-Dist: python-dotenv (==0.19.2)
Requires-Dist: pytz (==2024.1)
Requires-Dist: six (==1.16.0)
Requires-Dist: stringcase (==1.2.0)
Requires-Dist: typing-extensions (==4.12.2)
Requires-Dist: webargs (==8.4.0)
Provides-Extra: dev
Requires-Dist: pytest ; extra == 'dev'
Requires-Dist: sphinx ; extra == 'dev'
